{
  "number": 5,
  "name": "\ud83d\udd27 MVP Week 1: Make It Not Broken",
  "focus": "mvp_week1_fix",
  "started": "2025-08-05T15:37:21.573782",
  "goal": "Fix 0 tests, eliminate ALL 500 errors \u2192 Zero crashes, all pages load",
  "tasks": [
    "Fix or disable 0 failing tests",
    "Find and fix ALL 500 errors on every page",
    "Ensure registration form works completely",
    "Ensure login persists session properly",
    "Fix meal plan generation (< 5 seconds)",
    "Fix save meal plan functionality",
    "Fix view saved plans page",
    "Ensure all pages load in < 3 seconds",
    "Test on Chrome, Firefox, Safari",
    "Test on mobile browsers (iOS/Android)",
    "Set up production deployment (Railway/Render)",
    "Configure production database (PostgreSQL)"
  ],
  "success_criteria": [
    "Can complete full user flow without ANY errors",
    "0 console errors on main pages",
    "All forms submit and save data properly",
    "Deployed to production URL (not localhost)",
    "< 3 second page load times"
  ],
  "estimated_duration": "1-2 days",
  "completed": "2025-08-05T15:37:21.574788",
  "review": {
    "sprint_number": 5,
    "sprint_name": "\ud83d\udd27 MVP Week 1: Make It Not Broken",
    "completion_rate": 0.0,
    "completed_tasks": [],
    "remaining_tasks": [
      "Fix or disable 0 failing tests",
      "Find and fix ALL 500 errors on every page",
      "Ensure registration form works completely",
      "Ensure login persists session properly",
      "Fix meal plan generation (< 5 seconds)",
      "Fix save meal plan functionality",
      "Fix view saved plans page",
      "Ensure all pages load in < 3 seconds",
      "Test on Chrome, Firefox, Safari",
      "Test on mobile browsers (iOS/Android)",
      "Set up production deployment (Railway/Render)",
      "Configure production database (PostgreSQL)"
    ],
    "metrics_improvement": [],
    "lessons_learned": [],
    "next_steps": [
      "Complete 12 remaining tasks"
    ]
  }
}